Compiled from "Test.java"
public class xuanfs.Test {
  public xuanfs.Test();
    Code:
       0: aload_0
       1: invokespecial #1                  // Method java/lang/Object."<init>":()V
       4: return

  public static java.lang.String getJobByUrl(java.lang.String, java.lang.String);
    Code:
       0: aconst_null
       1: astore_2
       2: aconst_null
       3: astore_3
       4: aconst_null
       5: astore        4
       7: aconst_null
       8: astore        5
      10: new           #2                  // class java/lang/StringBuffer
      13: dup
      14: invokespecial #3                  // Method java/lang/StringBuffer."<init>":()V
      17: astore        6
      19: new           #4                  // class java/net/URL
      22: dup
      23: aload_0
      24: invokespecial #5                  // Method java/net/URL."<init>":(Ljava/lang/String;)V
      27: astore_2
      28: aload_2
      29: invokevirtual #6                  // Method java/net/URL.openConnection:()Ljava/net/URLConnection;
      32: astore_3
      33: new           #7                  // class java/io/InputStreamReader
      36: dup
      37: aload_3
      38: invokevirtual #8                  // Method java/net/URLConnection.getInputStream:()Ljava/io/InputStream;
      41: aload_1
      42: invokespecial #9                  // Method java/io/InputStreamReader."<init>":(Ljava/io/InputStream;Ljava/lang/String;)V
      45: astore        4
      47: new           #10                 // class java/io/BufferedReader
      50: dup
      51: aload         4
      53: invokespecial #11                 // Method java/io/BufferedReader."<init>":(Ljava/io/Reader;)V
      56: astore        5
      58: aconst_null
      59: astore        7
      61: aload         5
      63: invokevirtual #12                 // Method java/io/BufferedReader.readLine:()Ljava/lang/String;
      66: dup
      67: astore        7
      69: ifnull        101
      72: aload         6
      74: new           #13                 // class java/lang/StringBuilder
      77: dup
      78: invokespecial #14                 // Method java/lang/StringBuilder."<init>":()V
      81: aload         7
      83: invokevirtual #15                 // Method java/lang/StringBuilder.append:(Ljava/lang/String;)Ljava/lang/StringBuilder;
      86: ldc           #16                 // String \n
      88: invokevirtual #15                 // Method java/lang/StringBuilder.append:(Ljava/lang/String;)Ljava/lang/StringBuilder;
      91: invokevirtual #17                 // Method java/lang/StringBuilder.toString:()Ljava/lang/String;
      94: invokevirtual #18                 // Method java/lang/StringBuffer.append:(Ljava/lang/String;)Ljava/lang/StringBuffer;
      97: pop
      98: goto          61
     101: aload         5
     103: invokevirtual #19                 // Method java/io/BufferedReader.close:()V
     106: aload         4
     108: invokevirtual #20                 // Method java/io/InputStreamReader.close:()V
     111: goto          179
     114: astore        7
     116: aload         7
     118: invokevirtual #22                 // Method java/lang/Exception.printStackTrace:()V
     121: goto          179
     124: astore        7
     126: aload         7
     128: invokevirtual #22                 // Method java/lang/Exception.printStackTrace:()V
     131: aload         5
     133: invokevirtual #19                 // Method java/io/BufferedReader.close:()V
     136: aload         4
     138: invokevirtual #20                 // Method java/io/InputStreamReader.close:()V
     141: goto          179
     144: astore        7
     146: aload         7
     148: invokevirtual #22                 // Method java/lang/Exception.printStackTrace:()V
     151: goto          179
     154: astore        8
     156: aload         5
     158: invokevirtual #19                 // Method java/io/BufferedReader.close:()V
     161: aload         4
     163: invokevirtual #20                 // Method java/io/InputStreamReader.close:()V
     166: goto          176
     169: astore        9
     171: aload         9
     173: invokevirtual #22                 // Method java/lang/Exception.printStackTrace:()V
     176: aload         8
     178: athrow
     179: aload         6
     181: invokevirtual #23                 // Method java/lang/StringBuffer.toString:()Ljava/lang/String;
     184: areturn
    Exception table:
       from    to  target type
         101   111   114   Class java/lang/Exception
          19   101   124   Class java/lang/Exception
         131   141   144   Class java/lang/Exception
          19   101   154   any
         124   131   154   any
         156   166   169   Class java/lang/Exception
         154   156   154   any

  public static void main(java.lang.String[]);
    Code:
       0: iconst_1
       1: istore_1
       2: new           #2                  // class java/lang/StringBuffer
       5: dup
       6: invokespecial #3                  // Method java/lang/StringBuffer."<init>":()V
       9: astore_2
      10: iload_1
      11: iconst_3
      12: if_icmpgt     394
      15: new           #13                 // class java/lang/StringBuilder
      18: dup
      19: invokespecial #14                 // Method java/lang/StringBuilder."<init>":()V
      22: ldc           #24                 // String https://search.51job.com/list/030200,000000,0000,00,2,99,java,2,
      24: invokevirtual #15                 // Method java/lang/StringBuilder.append:(Ljava/lang/String;)Ljava/lang/StringBuilder;
      27: iload_1
      28: invokevirtual #25                 // Method java/lang/StringBuilder.append:(I)Ljava/lang/StringBuilder;
      31: ldc           #26                 // String .html?lang=c&postchannel=0000&workyear=01&cotype=99&degreefrom=99&jobterm=99&companysize=99&ord_field=0&dibiaoid=0&line=&welfare=
      33: invokevirtual #15                 // Method java/lang/StringBuilder.append:(Ljava/lang/String;)Ljava/lang/StringBuilder;
      36: invokevirtual #17                 // Method java/lang/StringBuilder.toString:()Ljava/lang/String;
      39: astore_3
      40: ldc           #27                 // String gbk
      42: astore        4
      44: aload_3
      45: aload         4
      47: invokestatic  #28                 // Method getJobByUrl:(Ljava/lang/String;Ljava/lang/String;)Ljava/lang/String;
      50: astore        5
      52: aload         5
      54: invokestatic  #29                 // Method org/jsoup/Jsoup.parse:(Ljava/lang/String;)Lorg/jsoup/nodes/Document;
      57: astore        6
      59: aload         6
      61: ldc           #30                 // String el
      63: invokevirtual #31                 // Method org/jsoup/nodes/Document.getElementsByClass:(Ljava/lang/String;)Lorg/jsoup/select/Elements;
      66: astore        7
      68: aload         7
      70: invokevirtual #32                 // Method org/jsoup/select/Elements.iterator:()Ljava/util/Iterator;
      73: astore        8
      75: aload         8
      77: invokeinterface #33,  1           // InterfaceMethod java/util/Iterator.hasNext:()Z
      82: ifeq          388
      85: aload         8
      87: invokeinterface #34,  1           // InterfaceMethod java/util/Iterator.next:()Ljava/lang/Object;
      92: checkcast     #35                 // class org/jsoup/nodes/Element
      95: astore        9
      97: aload         9
      99: ldc           #36                 // String t1
     101: invokevirtual #37                 // Method org/jsoup/nodes/Element.getElementsByClass:(Ljava/lang/String;)Lorg/jsoup/select/Elements;
     104: invokevirtual #38                 // Method org/jsoup/select/Elements.text:()Ljava/lang/String;
     107: astore        10
     109: aload         9
     111: ldc           #39                 // String t2
     113: invokevirtual #37                 // Method org/jsoup/nodes/Element.getElementsByClass:(Ljava/lang/String;)Lorg/jsoup/select/Elements;
     116: invokevirtual #38                 // Method org/jsoup/select/Elements.text:()Ljava/lang/String;
     119: astore        11
     121: aload         9
     123: ldc           #40                 // String t3
     125: invokevirtual #37                 // Method org/jsoup/nodes/Element.getElementsByClass:(Ljava/lang/String;)Lorg/jsoup/select/Elements;
     128: invokevirtual #38                 // Method org/jsoup/select/Elements.text:()Ljava/lang/String;
     131: astore        12
     133: aload         9
     135: ldc           #41                 // String t4
     137: invokevirtual #37                 // Method org/jsoup/nodes/Element.getElementsByClass:(Ljava/lang/String;)Lorg/jsoup/select/Elements;
     140: invokevirtual #38                 // Method org/jsoup/select/Elements.text:()Ljava/lang/String;
     143: astore        13
     145: aload         9
     147: ldc           #42                 // String t5
     149: invokevirtual #37                 // Method org/jsoup/nodes/Element.getElementsByClass:(Ljava/lang/String;)Lorg/jsoup/select/Elements;
     152: invokevirtual #38                 // Method org/jsoup/select/Elements.text:()Ljava/lang/String;
     155: astore        14
     157: aload         9
     159: ldc           #43                 // String a
     161: invokevirtual #44                 // Method org/jsoup/nodes/Element.select:(Ljava/lang/String;)Lorg/jsoup/select/Elements;
     164: ldc           #45                 // String href
     166: invokevirtual #46                 // Method org/jsoup/select/Elements.attr:(Ljava/lang/String;)Ljava/lang/String;
     169: astore        15
     171: ldc           #47                 // String
     173: aload         10
     175: invokevirtual #48                 // Method java/lang/String.equals:(Ljava/lang/Object;)Z
     178: ifne          385
     181: aload_2
     182: new           #13                 // class java/lang/StringBuilder
     185: dup
     186: invokespecial #14                 // Method java/lang/StringBuilder."<init>":()V
     189: ldc           #49                 // String \r\n职位:
     191: invokevirtual #15                 // Method java/lang/StringBuilder.append:(Ljava/lang/String;)Ljava/lang/StringBuilder;
     194: aload         10
     196: invokevirtual #15                 // Method java/lang/StringBuilder.append:(Ljava/lang/String;)Ljava/lang/StringBuilder;
     199: ldc           #50                 // String \r\n公司:
     201: invokevirtual #15                 // Method java/lang/StringBuilder.append:(Ljava/lang/String;)Ljava/lang/StringBuilder;
     204: aload         11
     206: invokevirtual #15                 // Method java/lang/StringBuilder.append:(Ljava/lang/String;)Ljava/lang/StringBuilder;
     209: ldc           #51                 // String \r\n地址:
     211: invokevirtual #15                 // Method java/lang/StringBuilder.append:(Ljava/lang/String;)Ljava/lang/StringBuilder;
     214: aload         12
     216: invokevirtual #15                 // Method java/lang/StringBuilder.append:(Ljava/lang/String;)Ljava/lang/StringBuilder;
     219: ldc           #52                 // String \r\n工资:
     221: invokevirtual #15                 // Method java/lang/StringBuilder.append:(Ljava/lang/String;)Ljava/lang/StringBuilder;
     224: aload         13
     226: invokevirtual #15                 // Method java/lang/StringBuilder.append:(Ljava/lang/String;)Ljava/lang/StringBuilder;
     229: ldc           #53                 // String \r\n发布日期:
     231: invokevirtual #15                 // Method java/lang/StringBuilder.append:(Ljava/lang/String;)Ljava/lang/StringBuilder;
     234: aload         14
     236: invokevirtual #15                 // Method java/lang/StringBuilder.append:(Ljava/lang/String;)Ljava/lang/StringBuilder;
     239: ldc           #54                 // String \r\n详细链接:
     241: invokevirtual #15                 // Method java/lang/StringBuilder.append:(Ljava/lang/String;)Ljava/lang/StringBuilder;
     244: aload         15
     246: invokevirtual #15                 // Method java/lang/StringBuilder.append:(Ljava/lang/String;)Ljava/lang/StringBuilder;
     249: ldc           #55                 // String \r\n
     251: invokevirtual #15                 // Method java/lang/StringBuilder.append:(Ljava/lang/String;)Ljava/lang/StringBuilder;
     254: invokevirtual #17                 // Method java/lang/StringBuilder.toString:()Ljava/lang/String;
     257: invokevirtual #18                 // Method java/lang/StringBuffer.append:(Ljava/lang/String;)Ljava/lang/StringBuffer;
     260: pop
     261: getstatic     #56                 // Field java/lang/System.out:Ljava/io/PrintStream;
     264: new           #13                 // class java/lang/StringBuilder
     267: dup
     268: invokespecial #14                 // Method java/lang/StringBuilder."<init>":()V
     271: ldc           #57                 // String job:
     273: invokevirtual #15                 // Method java/lang/StringBuilder.append:(Ljava/lang/String;)Ljava/lang/StringBuilder;
     276: aload         10
     278: invokevirtual #15                 // Method java/lang/StringBuilder.append:(Ljava/lang/String;)Ljava/lang/StringBuilder;
     281: invokevirtual #17                 // Method java/lang/StringBuilder.toString:()Ljava/lang/String;
     284: invokevirtual #58                 // Method java/io/PrintStream.println:(Ljava/lang/String;)V
     287: getstatic     #56                 // Field java/lang/System.out:Ljava/io/PrintStream;
     290: new           #13                 // class java/lang/StringBuilder
     293: dup
     294: invokespecial #14                 // Method java/lang/StringBuilder."<init>":()V
     297: ldc           #59                 // String \tcompany:
     299: invokevirtual #15                 // Method java/lang/StringBuilder.append:(Ljava/lang/String;)Ljava/lang/StringBuilder;
     302: aload         11
     304: invokevirtual #15                 // Method java/lang/StringBuilder.append:(Ljava/lang/String;)Ljava/lang/StringBuilder;
     307: invokevirtual #17                 // Method java/lang/StringBuilder.toString:()Ljava/lang/String;
     310: invokevirtual #58                 // Method java/io/PrintStream.println:(Ljava/lang/String;)V
     313: getstatic     #56                 // Field java/lang/System.out:Ljava/io/PrintStream;
     316: new           #13                 // class java/lang/StringBuilder
     319: dup
     320: invokespecial #14                 // Method java/lang/StringBuilder."<init>":()V
     323: ldc           #60                 // String \taddress:
     325: invokevirtual #15                 // Method java/lang/StringBuilder.append:(Ljava/lang/String;)Ljava/lang/StringBuilder;
     328: aload         12
     330: invokevirtual #15                 // Method java/lang/StringBuilder.append:(Ljava/lang/String;)Ljava/lang/StringBuilder;
     333: ldc           #61                 // String \tsalary:
     335: invokevirtual #15                 // Method java/lang/StringBuilder.append:(Ljava/lang/String;)Ljava/lang/StringBuilder;
     338: aload         13
     340: invokevirtual #15                 // Method java/lang/StringBuilder.append:(Ljava/lang/String;)Ljava/lang/StringBuilder;
     343: ldc           #62                 // String \tday:
     345: invokevirtual #15                 // Method java/lang/StringBuilder.append:(Ljava/lang/String;)Ljava/lang/StringBuilder;
     348: aload         14
     350: invokevirtual #15                 // Method java/lang/StringBuilder.append:(Ljava/lang/String;)Ljava/lang/StringBuilder;
     353: invokevirtual #17                 // Method java/lang/StringBuilder.toString:()Ljava/lang/String;
     356: invokevirtual #58                 // Method java/io/PrintStream.println:(Ljava/lang/String;)V
     359: getstatic     #56                 // Field java/lang/System.out:Ljava/io/PrintStream;
     362: new           #13                 // class java/lang/StringBuilder
     365: dup
     366: invokespecial #14                 // Method java/lang/StringBuilder."<init>":()V
     369: ldc           #63                 // String \thref:
     371: invokevirtual #15                 // Method java/lang/StringBuilder.append:(Ljava/lang/String;)Ljava/lang/StringBuilder;
     374: aload         15
     376: invokevirtual #15                 // Method java/lang/StringBuilder.append:(Ljava/lang/String;)Ljava/lang/StringBuilder;
     379: invokevirtual #17                 // Method java/lang/StringBuilder.toString:()Ljava/lang/String;
     382: invokevirtual #58                 // Method java/io/PrintStream.println:(Ljava/lang/String;)V
     385: goto          75
     388: iinc          1, 1
     391: goto          10
     394: new           #64                 // class java/io/FileOutputStream
     397: dup
     398: ldc           #65                 // String d:/job.txt
     400: invokespecial #66                 // Method java/io/FileOutputStream."<init>":(Ljava/lang/String;)V
     403: astore_3
     404: aload_2
     405: invokevirtual #23                 // Method java/lang/StringBuffer.toString:()Ljava/lang/String;
     408: invokevirtual #67                 // Method java/lang/String.getBytes:()[B
     411: astore        4
     413: aload_3
     414: aload         4
     416: invokevirtual #68                 // Method java/io/FileOutputStream.write:([B)V
     419: getstatic     #56                 // Field java/lang/System.out:Ljava/io/PrintStream;
     422: ldc           #69                 // String 导出完成！
     424: invokevirtual #58                 // Method java/io/PrintStream.println:(Ljava/lang/String;)V
     427: aload_3
     428: invokevirtual #70                 // Method java/io/FileOutputStream.close:()V
     431: goto          439
     434: astore_3
     435: aload_3
     436: invokevirtual #22                 // Method java/lang/Exception.printStackTrace:()V
     439: return
    Exception table:
       from    to  target type
         394   431   434   Class java/lang/Exception
}
